setup.cfg
setup.py
hostexpand/HostExpander.py
hostexpand/__init__.py
hostexpand.egg-info/PKG-INFO
hostexpand.egg-info/SOURCES.txt
hostexpand.egg-info/dependency_links.txt
hostexpand.egg-info/requires.txt
hostexpand.egg-info/top_level.txt
hostexpand.egg-info/zip-safe
scripts/hostexpand