Metadata-Version: 1.1
Name: hostexpand
Version: 1.0.2
Summary: A tool to expand hostnames based on a pattern language and DNS resolution
Home-page: https://github.com/yadt/hostexpand
Author: Arne Hilmann, Alexander Metzner, Udo Juettner
Author-email: arne.hilmann@gmail.com, alexander.metzner@gmail.com, udo.juettner@gmail.com
License: GNU GPL v3
Platform: UNKNOWN
Classifier: Development Status :: 5 - Production/Stable
Classifier: Environment :: Console
Classifier: Intended Audience :: Developers
Classifier: Intended Audience :: System Administrators
Classifier: License :: OSI Approved :: GNU General Public License (GPL)
Classifier: Programming Language :: Python
Classifier: Topic :: System :: Networking
Classifier: Topic :: System :: Software Distribution
Classifier: Topic :: System :: Systems Administration
